.gitignore
MANIFEST.in
README.txt
bootstrap.py
buildout.cfg
setup.cfg
setup.py
versions.cfg
docs/HISTORY.txt
wildcard/__init__.py
wildcard.cleanprint.egg-info/PKG-INFO
wildcard.cleanprint.egg-info/SOURCES.txt
wildcard.cleanprint.egg-info/dependency_links.txt
wildcard.cleanprint.egg-info/entry_points.txt
wildcard.cleanprint.egg-info/namespace_packages.txt
wildcard.cleanprint.egg-info/not-zip-safe
wildcard.cleanprint.egg-info/requires.txt
wildcard.cleanprint.egg-info/top_level.txt
wildcard/cleanprint/__init__.py
wildcard/cleanprint/configure.zcml
wildcard/cleanprint/controlpanel.py
wildcard/cleanprint/interfaces.py
wildcard/cleanprint/Extensions/Install.py
wildcard/cleanprint/Extensions/__init__.py
wildcard/cleanprint/profiles/default/actions.xml
wildcard/cleanprint/profiles/default/browserlayer.xml
wildcard/cleanprint/profiles/default/controlpanel.xml
wildcard/cleanprint/profiles/default/metadata.xml
wildcard/cleanprint/profiles/default/registry.xml
wildcard/cleanprint/profiles/default/wildcard.cleanprint.txt
wildcard/cleanprint/profiles/uninstall/actions.xml
wildcard/cleanprint/profiles/uninstall/controlpanel.xml
wildcard/cleanprint/profiles/uninstall/registry.xml