Metadata-Version: 1.0
Name: wildcard.cleanprint
Version: 1.0a4
Summary: Clean Print integration for Plone
Home-page: http://github.com/collective/wildcard.cleanprint
Author: Joel Kleier
Author-email: joel.kleier@gmail.com
License: GPL
Keywords: plone cleanprint
Platform: UNKNOWN
Classifier: Framework :: Plone
Classifier: Programming Language :: Python
